bbb_dl/__init__.py
bbb_dl/batch.py
bbb_dl/ffmpeg.py
bbb_dl/main.py
bbb_dl/utils.py
bbb_dl/version.py
bbb_dl-1.0.13.dist-info/AUTHORS
bbb_dl-1.0.13.dist-info/LICENSE
bbb_dl-1.0.13.dist-info/METADATA
bbb_dl-1.0.13.dist-info/WHEEL
bbb_dl-1.0.13.dist-info/entry_points.txt
bbb_dl-1.0.13.dist-info/top_level.txt
bbb_dl-1.0.13.dist-info/RECORD
