Metadata-Version: 2.1
Name: bbb-dl
Version: 1.0.13
Summary: Big Blue Button Downloader that downloads a BBB lesson as MP4 video
Home-page: https://github.com/C0D3D3V/bbb-dl
Author: C0D3D3V
License: GPL-2.0
Classifier: Development Status :: 4 - Beta
Classifier: Intended Audience :: End Users/Desktop
Classifier: License :: OSI Approved :: MIT License
Classifier: Programming Language :: Python :: 3 :: Only
Classifier: Topic :: Education
Classifier: Topic :: Internet :: WWW/HTTP :: Indexing/Search
Classifier: Topic :: Multimedia :: Video
Classifier: Topic :: Multimedia :: Sound/Audio
Classifier: Topic :: Utilities
Requires-Python: >=3.7
License-File: LICENSE
License-File: AUTHORS
Requires-Dist: aiofiles>=22.1.0
Requires-Dist: aiohttp>=3.8.3
Requires-Dist: certifi>=2020.4.5.2
Requires-Dist: colorama>=0.4.6
Requires-Dist: playwright>=1.29.0
Requires-Dist: python-ffmpeg>=2.0.12
Requires-Dist: requests>=2.24.0
